{
  "format_version": "1.20.10",
  "minecraft:recipe_shaped": {
    "description": {
    "identifier": "djc:iron_scythe"
    },

    
    "tags": [ "crafting_table" ],
    "pattern": [
      "XXX",
      "X S",
      "  S"
    ],
    "key": {
      "X": {
        "item": "minecraft:iron_ingot"
      },
      "S": {
        "item": "minecraft:stick"
      }
    },
	"unlock": [
        {
          "item": "minecraft:iron_ingot"
        }
    ],
    "result": {
      "item": "djc:iron_scythe"
    }
  }
}
